odoo/addons/ssi_consolidated_financial_statement/README.rst
odoo/addons/ssi_consolidated_financial_statement/__init__.py
odoo/addons/ssi_consolidated_financial_statement/__manifest__.py
odoo/addons/ssi_consolidated_financial_statement/menu.xml
odoo/addons/ssi_consolidated_financial_statement/data/approval_template/elimination_entry.xml
odoo/addons/ssi_consolidated_financial_statement/data/approval_template/fs_consolidation_ws.xml
odoo/addons/ssi_consolidated_financial_statement/data/approval_template/subsidiary_tb_adjustment_entry.xml
odoo/addons/ssi_consolidated_financial_statement/data/approval_template/subsidiary_trial_balance.xml
odoo/addons/ssi_consolidated_financial_statement/data/ir_sequence/elimination_entry.xml
odoo/addons/ssi_consolidated_financial_statement/data/ir_sequence/fs_consolidation_ws.xml
odoo/addons/ssi_consolidated_financial_statement/data/ir_sequence/subsidiary_tb_adjustment_entry.xml
odoo/addons/ssi_consolidated_financial_statement/data/ir_sequence/subsidiary_trial_balance.xml
odoo/addons/ssi_consolidated_financial_statement/data/policy_template/elimination_entry.xml
odoo/addons/ssi_consolidated_financial_statement/data/policy_template/fs_consolidation_ws.xml
odoo/addons/ssi_consolidated_financial_statement/data/policy_template/subsidiary_tb_adjustment_entry.xml
odoo/addons/ssi_consolidated_financial_statement/data/policy_template/subsidiary_trial_balance.xml
odoo/addons/ssi_consolidated_financial_statement/data/sequence_template/elimination_entry.xml
odoo/addons/ssi_consolidated_financial_statement/data/sequence_template/fs_consolidation_ws.xml
odoo/addons/ssi_consolidated_financial_statement/data/sequence_template/subsidiary_tb_adjustment_entry.xml
odoo/addons/ssi_consolidated_financial_statement/data/sequence_template/subsidiary_trial_balance.xml
odoo/addons/ssi_consolidated_financial_statement/models/__init__.py
odoo/addons/ssi_consolidated_financial_statement/models/elimination_entry.py
odoo14_addon_ssi_consolidated_financial_statement-14.0.1.0.0.dist-info/METADATA
odoo14_addon_ssi_consolidated_financial_statement-14.0.1.0.0.dist-info/WHEEL
odoo14_addon_ssi_consolidated_financial_statement-14.0.1.0.0.dist-info/top_level.txt
odoo14_addon_ssi_consolidated_financial_statement-14.0.1.0.0.dist-info/RECORD
